LICENSE.txt
MANIFEST.in
README.rst
setup.cfg
setup.py
pyrealsense/__init__.py
pyrealsense/constants.py
pyrealsense/importlib.py
pyrealsense/offline.py
pyrealsense/rsutilwrapper.c
pyrealsense/stream.py
pyrealsense/to_wrap.py
pyrealsense/utils.py
pyrealsense.egg-info/PKG-INFO
pyrealsense.egg-info/SOURCES.txt
pyrealsense.egg-info/dependency_links.txt
pyrealsense.egg-info/requires.txt
pyrealsense.egg-info/top_level.txt