Metadata-Version: 1.1
Name: pyrealsense
Version: 1.4
Summary: Simple ctypes extension to the librealsense library for Linux and Mac OS
Home-page: https://github.com/toinsson/pyrealsense
Author: Antoine Loriette
Author-email: antoine.loriette@gmail.com
License: Apache
Keywords: realsense
Platform: UNKNOWN
Classifier: Development Status :: 3 - Alpha
Classifier: Intended Audience :: Developers
Classifier: License :: OSI Approved :: Apache Software License
Classifier: Topic :: System :: Hardware
